[
  {
    "name": "Arcadian 2024 HD",
    "url": "http://royalfashion.design:80/movie/Norman/Norman123/1733688.mkv",
    "group": "Science Fiction"
  },
  {
    "name": "Resurrected - 2023",
    "url": "http://royalfashion.design:80/movie/Norman/Norman123/1737325.mp4",
    "group": "Science Fiction"
  },
  {
    "name": "Guardians of the Galaxy Vol. 2 - 2017",
    "url": "http://royalfashion.design:80/movie/Norman/Norman123/1737303.mkv",
    "group": "Science Fiction"
  },
  {
    "name": "The Courier - 2022",
    "url": "http://royalfashion.design:80/movie/Norman/Norman123/1734326.mkv",
    "group": "Science Fiction"
  },
  {
    "name": "Upload - 2021",
    "url": "http://royalfashion.design:80/movie/Norman/Norman123/1734147.mp4",
    "group": "Science Fiction"
  },
  {
    "name": "Double Blind - 2024",
    "url": "http://royalfashion.design:80/movie/Norman/Norman123/1726830.mp4",
    "group": "Science Fiction"
  },
  {
    "name": "Attack of the Meth Gator (2023)",
    "url": "http://royalfashion.design:80/movie/Norman/Norman123/1726018.mkv",
    "group": "Science Fiction"
  },
  {
    "name": "Southland Tales - 2006",
    "url": "http://royalfashion.design:80/movie/Norman/Norman123/1720421.mp4",
    "group": "Science Fiction"
  },
  {
    "name": "Implanted - 2021",
    "url": "http://royalfashion.design:80/movie/Norman/Norman123/1720169.mp4",
    "group": "Science Fiction"
  },
  {
    "name": "Come True - 2020",
    "url": "http://royalfashion.design:80/movie/Norman/Norman123/1719856.mp4",
    "group": "Science Fiction"
  },
  {
    "name": " I'm from the Future - 2023\" tvg-logo=\"http://smarter.infinitytv.world:80/images//lF0xbAJatRiBk8UNQ82ufi2vdjP.jpg\" group-title=\"Science Fiction\",Relax, I'm from the Future - 2023",
    "url": "http://royalfashion.design:80/movie/Norman/Norman123/1716328.mkv",
    "group": "Science Fiction"
  },
  {
    "name": "2067 - 2020",
    "url": "http://royalfashion.design:80/movie/Norman/Norman123/1582488.mkv",
    "group": "Science Fiction"
  },
  {
    "name": "Ad Astra - 2019",
    "url": "http://royalfashion.design:80/movie/Norman/Norman123/1583033.mp4",
    "group": "Science Fiction"
  },
  {
    "name": "Anti Matter - 2016",
    "url": "http://royalfashion.design:80/movie/Norman/Norman123/1579972.mkv",
    "group": "Science Fiction"
  },
  {
    "name": "Archive - 2020",
    "url": "http://royalfashion.design:80/movie/Norman/Norman123/1577329.mkv",
    "group": "Science Fiction"
  },
  {
    "name": "Batman: Under the Red Hood - 2010",
    "url": "http://royalfashion.design:80/movie/Norman/Norman123/1581802.mp4",
    "group": "Science Fiction"
  },
  {
    "name": "Before I'm Dead - 2021",
    "url": "http://royalfashion.design:80/movie/Norman/Norman123/1578922.mp4",
    "group": "Science Fiction"
  },
  {
    "name": "Blade Runner 2049 - 2017",
    "url": "http://royalfashion.design:80/movie/Norman/Norman123/1591013.mkv",
    "group": "Science Fiction"
  },
  {
    "name": "Comment je suis devenu super-héros - 2020",
    "url": "http://royalfashion.design:80/movie/Norman/Norman123/1579233.mkv",
    "group": "Science Fiction"
  },
  {
    "name": "D.O.D.: Day of Destiny - 2021",
    "url": "http://royalfashion.design:80/movie/Norman/Norman123/1578262.mp4",
    "group": "Science Fiction"
  },
  {
    "name": "Dark Phoenix - 2019",
    "url": "http://royalfashion.design:80/movie/Norman/Norman123/1583504.mkv",
    "group": "Science Fiction"
  },
  {
    "name": "Destination Marfa - 2021",
    "url": "http://royalfashion.design:80/movie/Norman/Norman123/1578276.mkv",
    "group": "Science Fiction"
  },
  {
    "name": "Don't Let Go - 2019",
    "url": "http://royalfashion.design:80/movie/Norman/Norman123/1582272.mp4",
    "group": "Science Fiction"
  },
  {
    "name": "Don't Look Deeper - 2022",
    "url": "http://royalfashion.design:80/movie/Norman/Norman123/1653181.mkv",
    "group": "Science Fiction"
  },
  {
    "name": "Doors - 2021",
    "url": "http://royalfashion.design:80/movie/Norman/Norman123/1578285.mp4",
    "group": "Science Fiction"
  },
  {
    "name": "Encounter - 2021",
    "url": "http://royalfashion.design:80/movie/Norman/Norman123/1576919.mp4",
    "group": "Science Fiction"
  },
  {
    "name": "Eternals - 2021",
    "url": "http://royalfashion.design:80/movie/Norman/Norman123/1576921.mp4",
    "group": "Science Fiction"
  },
  {
    "name": "Exodus - 2021",
    "url": "http://royalfashion.design:80/movie/Norman/Norman123/1578304.mp4",
    "group": "Science Fiction"
  },
  {
    "name": "Expulsion - 2020",
    "url": "http://royalfashion.design:80/movie/Norman/Norman123/1577535.mkv",
    "group": "Science Fiction"
  },
  {
    "name": "Gray Matter - 2023",
    "url": "http://royalfashion.design:80/movie/Norman/Norman123/1663583.mp4",
    "group": "Science Fiction"
  },
  {
    "name": "Infected: The Darkest Day - 2021",
    "url": "http://royalfashion.design:80/movie/Norman/Norman123/1580260.mp4",
    "group": "Science Fiction"
  },
  {
    "name": "In the Shadow of the Moon - 2019",
    "url": "http://royalfashion.design:80/movie/Norman/Norman123/1581945.mkv",
    "group": "Science Fiction"
  },
  {
    "name": "Next Exit - 2022",
    "url": "http://royalfashion.design:80/movie/Norman/Norman123/1653288.mp4",
    "group": "Science Fiction"
  },
  {
    "name": "Norman - 2021",
    "url": "http://royalfashion.design:80/movie/Norman/Norman123/1577743.mkv",
    "group": "Science Fiction"
  },
  {
    "name": "Only - 2020",
    "url": "http://royalfashion.design:80/movie/Norman/Norman123/1580406.mp4",
    "group": "Science Fiction"
  },
  {
    "name": "Post Impact - 2004",
    "url": "http://royalfashion.design:80/movie/Norman/Norman123/1579498.mkv",
    "group": "Science Fiction"
  },
  {
    "name": "Space - 2020",
    "url": "http://royalfashion.design:80/movie/Norman/Norman123/1583382.mkv",
    "group": "Science Fiction"
  },
  {
    "name": "Superman/Batman: Apocalypse - 2010",
    "url": "http://royalfashion.design:80/movie/Norman/Norman123/1581804.mp4",
    "group": "Science Fiction"
  },
  {
    "name": "Superman/Batman: Public Enemies - 2009",
    "url": "http://royalfashion.design:80/movie/Norman/Norman123/1653550.mp4",
    "group": "Science Fiction"
  },
  {
    "name": "Superman: Red Son - 2020",
    "url": "http://royalfashion.design:80/movie/Norman/Norman123/1591593.mp4",
    "group": "Science Fiction"
  },
  {
    "name": "Synchronic - 2020",
    "url": "http://royalfashion.design:80/movie/Norman/Norman123/1653607.mp4",
    "group": "Science Fiction"
  },
  {
    "name": "The Borrower - 1991",
    "url": "http://royalfashion.design:80/movie/Norman/Norman123/1578647.mp4",
    "group": "Science Fiction"
  },
  {
    "name": "The Complex: Lockdown - 2020",
    "url": "http://royalfashion.design:80/movie/Norman/Norman123/1577961.mkv",
    "group": "Science Fiction"
  },
  {
    "name": "The Gateway - 2018",
    "url": "http://royalfashion.design:80/movie/Norman/Norman123/1582611.mp4",
    "group": "Science Fiction"
  },
  {
    "name": "The Generator - 2017",
    "url": "http://royalfashion.design:80/movie/Norman/Norman123/1579714.mp4",
    "group": "Science Fiction"
  },
  {
    "name": "The Good Neighbour - 2019",
    "url": "http://royalfashion.design:80/movie/Norman/Norman123/1579718.mp4",
    "group": "Science Fiction"
  },
  {
    "name": "The Hunger Games - 2012",
    "url": "http://royalfashion.design:80/movie/Norman/Norman123/1582125.mp4",
    "group": "Science Fiction"
  },
  {
    "name": "The Hunger Games: Mockingjay - Part 1 - 2014",
    "url": "http://royalfashion.design:80/movie/Norman/Norman123/1577072.mkv",
    "group": "Science Fiction"
  },
  {
    "name": "The Hunger Games: Mockingjay - Part 1 - 2014",
    "url": "http://royalfashion.design:80/movie/Norman/Norman123/1584538.mkv",
    "group": "Science Fiction"
  },
  {
    "name": "The Immortal - 2019",
    "url": "http://royalfashion.design:80/movie/Norman/Norman123/1578687.mp4",
    "group": "Science Fiction"
  },
  {
    "name": "The Mandela Effect - 2019",
    "url": "http://royalfashion.design:80/movie/Norman/Norman123/1583446.mkv",
    "group": "Science Fiction"
  },
  {
    "name": "The Pod Generation - 2023",
    "url": "http://royalfashion.design:80/movie/Norman/Norman123/1675381.mkv",
    "group": "Science Fiction"
  },
  {
    "name": "Vesper - 2022",
    "url": "http://royalfashion.design:80/movie/Norman/Norman123/1653829.mp4",
    "group": "Science Fiction"
  },
  {
    "name": "Maid Droid - 2023",
    "url": "http://royalfashion.design:80/movie/Norman/Norman123/1679162.mkv",
    "group": "Science Fiction"
  },
  {
    "name": "Static Codes - 2023",
    "url": "http://royalfashion.design:80/movie/Norman/Norman123/1695220.mkv",
    "group": "Science Fiction"
  },
  {
    "name": "Terminator: Dark Fate - 2019",
    "url": "http://royalfashion.design:80/movie/Norman/Norman123/1759568.mp4",
    "group": "Science Fiction"
  },
  {
    "name": "Judge Dredd 1995 Hindi",
    "url": "http://royalfashion.design:80/movie/Norman/Norman123/1763063.mp4",
    "group": "Science Fiction"
  },
  {
    "name": "The White King (2016)",
    "url": "http://royalfashion.design:80/movie/Norman/Norman123/1760875.mp4",
    "group": "Science Fiction"
  },
  {
    "name": "TRON: The Next Day - 2011",
    "url": "http://royalfashion.design:80/movie/Norman/Norman123/1734419.mkv",
    "group": "Science Fiction"
  },
  {
    "name": "The Shift - 2023",
    "url": "http://royalfashion.design:80/movie/Norman/Norman123/1728330.mkv",
    "group": "Science Fiction"
  },
  {
    "name": "Slash/Back - 2022",
    "url": "http://royalfashion.design:80/movie/Norman/Norman123/1716686.mp4",
    "group": "Science Fiction"
  },
  {
    "name": "City Rush 3 - 2023",
    "url": "http://royalfashion.design:80/movie/Norman/Norman123/1715745.mp4",
    "group": "Science Fiction"
  },
  {
    "name": "Robot Apocalypse - 2021",
    "url": "http://royalfashion.design:80/movie/Norman/Norman123/1715692.mp4",
    "group": "Science Fiction"
  },
  {
    "name": "Star Trek - 2009",
    "url": "http://royalfashion.design:80/movie/Norman/Norman123/1591584.mkv",
    "group": "Science Fiction"
  },
  {
    "name": "Judge Dredd (1995)",
    "url": "http://royalfashion.design:80/movie/Norman/Norman123/1577661.mkv",
    "group": "Science Fiction"
  },
  {
    "name": "Jiu Jitsu (2020)",
    "url": "http://royalfashion.design:80/movie/Norman/Norman123/1781645.mkv",
    "group": "Science Fiction"
  },
  {
    "name": "Alien: Rubicon (2024)",
    "url": "http://royalfashion.design:80/movie/Norman/Norman123/1781027.mp4",
    "group": "Science Fiction"
  },
  {
    "name": "Sentinel (2024)",
    "url": "http://royalfashion.design:80/movie/Norman/Norman123/1780858.mp4",
    "group": "Science Fiction"
  },
  {
    "name": "Arcadian 2024 HD",
    "url": "http://royalfashion.design:80/movie/Lucky/Lucky123/1733688.mkv",
    "group": "Science Fiction"
  },
  {
    "name": "Double Blind - 2024",
    "url": "http://royalfashion.design:80/movie/Lucky/Lucky123/1726830.mp4",
    "group": "Science Fiction"
  },
  {
    "name": "Synapse - 2021",
    "url": "http://royalfashion.design:80/movie/Lucky/Lucky123/1720036.mp4",
    "group": "Science Fiction"
  },
  {
    "name": "Come True - 2020",
    "url": "http://royalfashion.design:80/movie/Lucky/Lucky123/1719856.mp4",
    "group": "Science Fiction"
  },
  {
    "name": "Max Cloud - 2020",
    "url": "http://royalfashion.design:80/movie/Lucky/Lucky123/1719751.mp4",
    "group": "Science Fiction"
  },
  {
    "name": "After Yang - 2022",
    "url": "http://royalfashion.design:80/movie/Lucky/Lucky123/1579939.mp4",
    "group": "Science Fiction"
  },
  {
    "name": "Alien Conquest - 2021",
    "url": "http://royalfashion.design:80/movie/Lucky/Lucky123/1578142.mp4",
    "group": "Science Fiction"
  },
  {
    "name": "Allegiance of Powers - 2016",
    "url": "http://royalfashion.design:80/movie/Lucky/Lucky123/1578862.mp4",
    "group": "Science Fiction"
  },
  {
    "name": "Batman: Gotham Knight - 2008",
    "url": "http://royalfashion.design:80/movie/Lucky/Lucky123/1577140.mp4",
    "group": "Science Fiction"
  },
  {
    "name": "Circle - 2015",
    "url": "http://royalfashion.design:80/movie/Lucky/Lucky123/1579001.mp4",
    "group": "Science Fiction"
  },
  {
    "name": "Collision Earth - 2020",
    "url": "http://royalfashion.design:80/movie/Lucky/Lucky123/1581848.mp4",
    "group": "Science Fiction"
  },
  {
    "name": "Colonials - 2023",
    "url": "http://royalfashion.design:80/movie/Lucky/Lucky123/1651101.mp4",
    "group": "Science Fiction"
  },
  {
    "name": "COVID-21: Lethal Virus - 2021",
    "url": "http://royalfashion.design:80/movie/Lucky/Lucky123/1578253.mp4",
    "group": "Science Fiction"
  },
  {
    "name": "Crater - 2023",
    "url": "http://royalfashion.design:80/movie/Lucky/Lucky123/1651224.mp4",
    "group": "Science Fiction"
  },
  {
    "name": "D.O.D.: Day of Destiny - 2021",
    "url": "http://royalfashion.design:80/movie/Lucky/Lucky123/1578262.mp4",
    "group": "Science Fiction"
  },
  {
    "name": "Dark Cloud - 2022",
    "url": "http://royalfashion.design:80/movie/Lucky/Lucky123/1653681.mp4",
    "group": "Science Fiction"
  },
  {
    "name": "Dark Skies - 2013",
    "url": "http://royalfashion.design:80/movie/Lucky/Lucky123/1581871.mkv",
    "group": "Science Fiction"
  },
  {
    "name": "Destination Marfa - 2021",
    "url": "http://royalfashion.design:80/movie/Lucky/Lucky123/1578276.mkv",
    "group": "Science Fiction"
  },
  {
    "name": "Deus - 2022",
    "url": "http://royalfashion.design:80/movie/Lucky/Lucky123/1653690.mp4",
    "group": "Science Fiction"
  },
  {
    "name": "Don't Look Deeper - 2022",
    "url": "http://royalfashion.design:80/movie/Lucky/Lucky123/1653181.mkv",
    "group": "Science Fiction"
  },
  {
    "name": "Don't Look Up - 2021",
    "url": "http://royalfashion.design:80/movie/Lucky/Lucky123/1576834.mkv",
    "group": "Science Fiction"
  },
  {
    "name": "Doors - 2021",
    "url": "http://royalfashion.design:80/movie/Lucky/Lucky123/1578285.mp4",
    "group": "Science Fiction"
  },
  {
    "name": "Elysium - 2013",
    "url": "http://royalfashion.design:80/movie/Lucky/Lucky123/1583228.mkv",
    "group": "Science Fiction"
  },
  {
    "name": "Encounter - 2021",
    "url": "http://royalfashion.design:80/movie/Lucky/Lucky123/1576919.mp4",
    "group": "Science Fiction"
  },
  {
    "name": "Loophole - 2019",
    "url": "http://royalfashion.design:80/movie/Lucky/Lucky123/1579355.mkv",
    "group": "Science Fiction"
  },
  {
    "name": "Monster Force Zero - 2020",
    "url": "http://royalfashion.design:80/movie/Lucky/Lucky123/1581988.mkv",
    "group": "Science Fiction"
  },
  {
    "name": "Moon - 2009",
    "url": "http://royalfashion.design:80/movie/Lucky/Lucky123/1583317.mkv",
    "group": "Science Fiction"
  },
  {
    "name": "Only - 2020",
    "url": "http://royalfashion.design:80/movie/Lucky/Lucky123/1580406.mp4",
    "group": "Science Fiction"
  },
  {
    "name": "Robots - 2023",
    "url": "http://royalfashion.design:80/movie/Lucky/Lucky123/1676431.mkv",
    "group": "Science Fiction"
  },
  {
    "name": "Robot Wars - 2016",
    "url": "http://royalfashion.design:80/movie/Lucky/Lucky123/1579539.mp4",
    "group": "Science Fiction"
  },
  {
    "name": "See You Yesterday - 2019",
    "url": "http://royalfashion.design:80/movie/Lucky/Lucky123/1582050.mkv",
    "group": "Science Fiction"
  },
  {
    "name": "Superman: Red Son - 2020",
    "url": "http://royalfashion.design:80/movie/Lucky/Lucky123/1591593.mp4",
    "group": "Science Fiction"
  },
  {
    "name": "Synchronic - 2020",
    "url": "http://royalfashion.design:80/movie/Lucky/Lucky123/1653607.mp4",
    "group": "Science Fiction"
  },
  {
    "name": "Teenage Mutant Ninja Turtles - 1990",
    "url": "http://royalfashion.design:80/movie/Lucky/Lucky123/1582596.mp4",
    "group": "Science Fiction"
  },
  {
    "name": "Teenage Mutant Ninja Turtles - 2014",
    "url": "http://royalfashion.design:80/movie/Lucky/Lucky123/1577049.mp4",
    "group": "Science Fiction"
  },
  {
    "name": "Teenage Mutant Ninja Turtles II: The Secret of the Ooze - 1991",
    "url": "http://royalfashion.design:80/movie/Lucky/Lucky123/1577051.mp4",
    "group": "Science Fiction"
  },
  {
    "name": "The Borrower - 1991",
    "url": "http://royalfashion.design:80/movie/Lucky/Lucky123/1578647.mp4",
    "group": "Science Fiction"
  },
  {
    "name": "The Endless - 2017",
    "url": "http://royalfashion.design:80/movie/Lucky/Lucky123/1582789.mp4",
    "group": "Science Fiction"
  },
  {
    "name": "The Good Neighbour - 2019",
    "url": "http://royalfashion.design:80/movie/Lucky/Lucky123/1579718.mp4",
    "group": "Science Fiction"
  },
  {
    "name": "The Hunger Games - 2012",
    "url": "http://royalfashion.design:80/movie/Lucky/Lucky123/1582125.mp4",
    "group": "Science Fiction"
  },
  {
    "name": "The Hunger Games: Mockingjay - Part 1 - 2014",
    "url": "http://royalfashion.design:80/movie/Lucky/Lucky123/1577072.mkv",
    "group": "Science Fiction"
  },
  {
    "name": "What Happened to Monday - 2017",
    "url": "http://royalfashion.design:80/movie/Lucky/Lucky123/1583503.mkv",
    "group": "Science Fiction"
  },
  {
    "name": "White Sky - 2021",
    "url": "http://royalfashion.design:80/movie/Lucky/Lucky123/1579900.mkv",
    "group": "Science Fiction"
  },
  {
    "name": "Blue Beetle - 2023",
    "url": "http://royalfashion.design:80/movie/Lucky/Lucky123/1678774.mkv",
    "group": "Science Fiction"
  },
  {
    "name": "No One Will Save You - 2023",
    "url": "http://royalfashion.design:80/movie/Lucky/Lucky123/1679014.mkv",
    "group": "Science Fiction"
  },
  {
    "name": "Static Codes - 2023",
    "url": "http://royalfashion.design:80/movie/Lucky/Lucky123/1695220.mkv",
    "group": "Science Fiction"
  },
  {
    "name": "A Quiet Place Part II (2021)",
    "url": "http://royalfashion.design:80/movie/Lucky/Lucky123/1739571.mkv",
    "group": "Science Fiction"
  },
  {
    "name": "Judge Dredd 1995 Hindi",
    "url": "http://royalfashion.design:80/movie/Lucky/Lucky123/1763063.mp4",
    "group": "Science Fiction"
  },
  {
    "name": "Brazil (1985)",
    "url": "http://royalfashion.design:80/movie/Lucky/Lucky123/1760219.mkv",
    "group": "Science Fiction"
  },
  {
    "name": "Mimic (1997)",
    "url": "http://royalfashion.design:80/movie/Lucky/Lucky123/1759141.mkv",
    "group": "Science Fiction"
  },
  {
    "name": "Welcome to Willits (2016)",
    "url": "http://royalfashion.design:80/movie/Lucky/Lucky123/1758390.mp4",
    "group": "Science Fiction"
  },
  {
    "name": "Time Trap - 2018",
    "url": "http://royalfashion.design:80/movie/Lucky/Lucky123/1735224.mp4",
    "group": "Science Fiction"
  },
  {
    "name": "Trancers 6: Life After Deth - 2002",
    "url": "http://royalfashion.design:80/movie/Lucky/Lucky123/1734548.mkv",
    "group": "Science Fiction"
  },
  {
    "name": "TRON: The Next Day - 2011",
    "url": "http://royalfashion.design:80/movie/Lucky/Lucky123/1734419.mkv",
    "group": "Science Fiction"
  },
  {
    "name": "A Million Days - 2023",
    "url": "http://royalfashion.design:80/movie/Lucky/Lucky123/1733841.mp4",
    "group": "Science Fiction"
  },
  {
    "name": "Wonder Woman: Bloodlines - 2019",
    "url": "http://royalfashion.design:80/movie/Lucky/Lucky123/1733781.mkv",
    "group": "Science Fiction"
  },
  {
    "name": "Battle: Los Angeles - 2011",
    "url": "http://royalfashion.design:80/movie/Lucky/Lucky123/1728418.mp4",
    "group": "Science Fiction"
  },
  {
    "name": "City Rush 3 - 2023",
    "url": "http://royalfashion.design:80/movie/Lucky/Lucky123/1716234.mkv",
    "group": "Science Fiction"
  },
  {
    "name": "Sentinel (2024)",
    "url": "http://royalfashion.design:80/movie/Lucky/Lucky123/1780858.mp4",
    "group": "Science Fiction"
  },
  {
    "name": "Arcadian 2024 HD",
    "url": "http://royalfashion.design:80/movie/Nelly/Nelly1/1733688.mkv",
    "group": "Science Fiction"
  },
  {
    "name": "Rim of the World - 2019",
    "url": "http://royalfashion.design:80/movie/Nelly/Nelly1/1720227.mp4",
    "group": "Science Fiction"
  },
  {
    "name": "Voyagers - 2021",
    "url": "http://royalfashion.design:80/movie/Nelly/Nelly1/1720089.mkv",
    "group": "Science Fiction"
  },
  {
    "name": "Synapse - 2021",
    "url": "http://royalfashion.design:80/movie/Nelly/Nelly1/1720036.mp4",
    "group": "Science Fiction"
  },
  {
    "name": "Contactee - 2021",
    "url": "http://royalfashion.design:80/movie/Nelly/Nelly1/1719858.mkv",
    "group": "Science Fiction"
  },
  {
    "name": "Captive State - 2019",
    "url": "http://royalfashion.design:80/movie/Nelly/Nelly1/1715570.mkv",
    "group": "Science Fiction"
  },
  {
    "name": "65 - 2023",
    "url": "http://royalfashion.design:80/movie/Nelly/Nelly1/1653472.mp4",
    "group": "Science Fiction"
  },
  {
    "name": "A-X-L",
    "url": "http://royalfashion.design:80/movie/Nelly/Nelly1/407068.mkv",
    "group": "Science Fiction"
  },
  {
    "name": "After Earth - 2013",
    "url": "http://royalfashion.design:80/movie/Nelly/Nelly1/1582496.mp4",
    "group": "Science Fiction"
  },
  {
    "name": "Andover - 2018",
    "url": "http://royalfashion.design:80/movie/Nelly/Nelly1/1656498.mp4",
    "group": "Science Fiction"
  },
  {
    "name": "Android Uprising - 2020",
    "url": "http://royalfashion.design:80/movie/Nelly/Nelly1/1581782.mkv",
    "group": "Science Fiction"
  },
  {
    "name": "Anna to the Infinite Power - 1983",
    "url": "http://royalfashion.design:80/movie/Nelly/Nelly1/1578880.mp4",
    "group": "Science Fiction"
  },
  {
    "name": "Annihilation - 2018",
    "url": "http://royalfashion.design:80/movie/Nelly/Nelly1/1583063.mkv",
    "group": "Science Fiction"
  },
  {
    "name": "Anon - 2018",
    "url": "http://royalfashion.design:80/movie/Nelly/Nelly1/1583065.mkv",
    "group": "Science Fiction"
  },
  {
    "name": "Anti Matter - 2016",
    "url": "http://royalfashion.design:80/movie/Nelly/Nelly1/1579972.mkv",
    "group": "Science Fiction"
  },
  {
    "name": "Archive - 2020",
    "url": "http://royalfashion.design:80/movie/Nelly/Nelly1/1577329.mkv",
    "group": "Science Fiction"
  },
  {
    "name": "Assassinaut",
    "url": "http://royalfashion.design:80/movie/Nelly/Nelly1/407208.mkv",
    "group": "Science Fiction"
  },
  {
    "name": "Battlefield 2025 - 2021",
    "url": "http://royalfashion.design:80/movie/Nelly/Nelly1/1583091.mkv",
    "group": "Science Fiction"
  },
  {
    "name": "Dark Skies - 2013",
    "url": "http://royalfashion.design:80/movie/Nelly/Nelly1/1581871.mkv",
    "group": "Science Fiction"
  },
  {
    "name": "Dawn of the Planet of the Apes - 2014",
    "url": "http://royalfashion.design:80/movie/Nelly/Nelly1/1583192.mkv",
    "group": "Science Fiction"
  },
  {
    "name": "Destination Marfa - 2021",
    "url": "http://royalfashion.design:80/movie/Nelly/Nelly1/1578276.mkv",
    "group": "Science Fiction"
  },
  {
    "name": "Doors - 2021",
    "url": "http://royalfashion.design:80/movie/Nelly/Nelly1/1578285.mp4",
    "group": "Science Fiction"
  },
  {
    "name": "Gemini Man - 2019",
    "url": "http://royalfashion.design:80/movie/Nelly/Nelly1/1576935.mkv",
    "group": "Science Fiction"
  },
  {
    "name": "Kill Switch - 2017",
    "url": "http://royalfashion.design:80/movie/Nelly/Nelly1/1580299.mp4",
    "group": "Science Fiction"
  },
  {
    "name": "Kin - 2018",
    "url": "http://royalfashion.design:80/movie/Nelly/Nelly1/1591370.mp4",
    "group": "Science Fiction"
  },
  {
    "name": "Lapsis - 2021",
    "url": "http://royalfashion.design:80/movie/Nelly/Nelly1/1577673.mp4",
    "group": "Science Fiction"
  },
  {
    "name": "Linoleum - 2023",
    "url": "http://royalfashion.design:80/movie/Nelly/Nelly1/1650955.mkv",
    "group": "Science Fiction"
  },
  {
    "name": "Loophole - 2019",
    "url": "http://royalfashion.design:80/movie/Nelly/Nelly1/1579355.mkv",
    "group": "Science Fiction"
  },
  {
    "name": "M3GAN - 2022",
    "url": "http://royalfashion.design:80/movie/Nelly/Nelly1/1653267.mkv",
    "group": "Science Fiction"
  },
  {
    "name": "Monster Force Zero - 2020",
    "url": "http://royalfashion.design:80/movie/Nelly/Nelly1/1581988.mkv",
    "group": "Science Fiction"
  },
  {
    "name": "Monsters of California - 2023",
    "url": "http://royalfashion.design:80/movie/Nelly/Nelly1/1693868.mp4",
    "group": "Science Fiction"
  },
  {
    "name": "Moonfall - 2022",
    "url": "http://royalfashion.design:80/movie/Nelly/Nelly1/1576985.mkv",
    "group": "Science Fiction"
  },
  {
    "name": "Next Exit - 2022",
    "url": "http://royalfashion.design:80/movie/Nelly/Nelly1/1653288.mp4",
    "group": "Science Fiction"
  },
  {
    "name": "Night Raiders - 2021",
    "url": "http://royalfashion.design:80/movie/Nelly/Nelly1/1653739.mkv",
    "group": "Science Fiction"
  },
  {
    "name": "Nova - 2021",
    "url": "http://royalfashion.design:80/movie/Nelly/Nelly1/1653291.mp4",
    "group": "Science Fiction"
  },
  {
    "name": "One Moment - 2023",
    "url": "http://royalfashion.design:80/movie/Nelly/Nelly1/1664931.mp4",
    "group": "Science Fiction"
  },
  {
    "name": "Philadelphia Experiment II - 1993",
    "url": "http://royalfashion.design:80/movie/Nelly/Nelly1/1578486.mp4",
    "group": "Science Fiction"
  },
  {
    "name": "Teenage Mutant Ninja Turtles - 1990",
    "url": "http://royalfashion.design:80/movie/Nelly/Nelly1/1582596.mp4",
    "group": "Science Fiction"
  },
  {
    "name": "Teenage Mutant Ninja Turtles - 2014",
    "url": "http://royalfashion.design:80/movie/Nelly/Nelly1/1577049.mp4",
    "group": "Science Fiction"
  },
  {
    "name": "Teenage Mutant Ninja Turtles II: The Secret of the Ooze - 1991",
    "url": "http://royalfashion.design:80/movie/Nelly/Nelly1/1577051.mp4",
    "group": "Science Fiction"
  },
  {
    "name": "The Thing Inside Us - 2021",
    "url": "http://royalfashion.design:80/movie/Nelly/Nelly1/1579811.mp4",
    "group": "Science Fiction"
  },
  {
    "name": "Vesper - 2022",
    "url": "http://royalfashion.design:80/movie/Nelly/Nelly1/1653829.mp4",
    "group": "Science Fiction"
  },
  {
    "name": "Vivarium - 2019",
    "url": "http://royalfashion.design:80/movie/Nelly/Nelly1/1591745.mp4",
    "group": "Science Fiction"
  },
  {
    "name": "War of the Worlds: The Attack - 2023",
    "url": "http://royalfashion.design:80/movie/Nelly/Nelly1/1651574.mp4",
    "group": "Science Fiction"
  },
  {
    "name": "White Sky - 2021",
    "url": "http://royalfashion.design:80/movie/Nelly/Nelly1/1579900.mkv",
    "group": "Science Fiction"
  },
  {
    "name": "Вторжение - 2020",
    "url": "http://royalfashion.design:80/movie/Nelly/Nelly1/1577645.mkv",
    "group": "Science Fiction"
  },
  {
    "name": "流浪地球 - 2019",
    "url": "http://royalfashion.design:80/movie/Nelly/Nelly1/1591713.mp4",
    "group": "Science Fiction"
  },
  {
    "name": "Blue Beetle - 2023",
    "url": "http://royalfashion.design:80/movie/Nelly/Nelly1/1678774.mkv",
    "group": "Science Fiction"
  },
  {
    "name": "No One Will Save You - 2023",
    "url": "http://royalfashion.design:80/movie/Nelly/Nelly1/1679014.mkv",
    "group": "Science Fiction"
  },
  {
    "name": "Terminator: Dark Fate - 2019",
    "url": "http://royalfashion.design:80/movie/Nelly/Nelly1/1759568.mp4",
    "group": "Science Fiction"
  },
  {
    "name": "Trancers 6: Life After Deth - 2002",
    "url": "http://royalfashion.design:80/movie/Nelly/Nelly1/1734548.mkv",
    "group": "Science Fiction"
  },
  {
    "name": "A Million Days - 2023",
    "url": "http://royalfashion.design:80/movie/Nelly/Nelly1/1733841.mp4",
    "group": "Science Fiction"
  },
  {
    "name": "Ghost Project - 2023",
    "url": "http://royalfashion.design:80/movie/Nelly/Nelly1/1716236.mkv",
    "group": "Science Fiction"
  },
  {
    "name": "City Rush 3 - 2023",
    "url": "http://royalfashion.design:80/movie/Nelly/Nelly1/1716234.mkv",
    "group": "Science Fiction"
  },
  {
    "name": "Judge Dredd (1995)",
    "url": "http://royalfashion.design:80/movie/Nelly/Nelly1/1577661.mkv",
    "group": "Science Fiction"
  },
  {
    "name": "Alien: Rubicon (2024)",
    "url": "http://royalfashion.design:80/movie/Nelly/Nelly1/1781027.mp4",
    "group": "Science Fiction"
  },
  {
    "name": "2073 (2024)",
    "url": "http://royalfashion.design:80/movie/Nelly/Nelly1/1780454.mp4",
    "group": "Science Fiction"
  },
  {
    "name": "Attack on Titan - 2022",
    "url": "http://royalfashion.design:80/movie/Monty/Monty123/1736288.mkv",
    "group": "Science Fiction"
  },
  {
    "name": "The Kitchen (2023)",
    "url": "http://royalfashion.design:80/movie/Monty/Monty123/1723215.mkv",
    "group": "Science Fiction"
  },
  {
    "name": "Settlers - 2021",
    "url": "http://royalfashion.design:80/movie/Monty/Monty123/1720413.mp4",
    "group": "Science Fiction"
  },
  {
    "name": "Finch - 2021",
    "url": "http://royalfashion.design:80/movie/Monty/Monty123/1720361.mp4",
    "group": "Science Fiction"
  },
  {
    "name": "Synapse - 2021",
    "url": "http://royalfashion.design:80/movie/Monty/Monty123/1720036.mp4",
    "group": "Science Fiction"
  },
  {
    "name": "Nemesis - 1992",
    "url": "http://royalfashion.design:80/movie/Monty/Monty123/1719926.mp4",
    "group": "Science Fiction"
  },
  {
    "name": "Final Frequency - 2021",
    "url": "http://royalfashion.design:80/movie/Monty/Monty123/1719873.mp4",
    "group": "Science Fiction"
  },
  {
    "name": "Archive - 2020",
    "url": "http://royalfashion.design:80/movie/Monty/Monty123/1577329.mkv",
    "group": "Science Fiction"
  },
  {
    "name": "Battlefield 2025 - 2021",
    "url": "http://royalfashion.design:80/movie/Monty/Monty123/1577353.mkv",
    "group": "Science Fiction"
  },
  {
    "name": "Battlefield 2025 - 2021",
    "url": "http://royalfashion.design:80/movie/Monty/Monty123/1583091.mkv",
    "group": "Science Fiction"
  },
  {
    "name": "Blade Runner - 1982",
    "url": "http://royalfashion.design:80/movie/Monty/Monty123/1591120.mp4",
    "group": "Science Fiction"
  },
  {
    "name": "Blade Runner 2049 - 2017",
    "url": "http://royalfashion.design:80/movie/Monty/Monty123/1583121.mkv",
    "group": "Science Fiction"
  },
  {
    "name": "Blade Runner 2049 - 2017",
    "url": "http://royalfashion.design:80/movie/Monty/Monty123/1591013.mkv",
    "group": "Science Fiction"
  },
  {
    "name": "Blank - 2022",
    "url": "http://royalfashion.design:80/movie/Monty/Monty123/1653669.mp4",
    "group": "Science Fiction"
  },
  {
    "name": "Cinderella 2000 - 1977",
    "url": "http://royalfashion.design:80/movie/Monty/Monty123/1578240.mp4",
    "group": "Science Fiction"
  },
  {
    "name": "Circle - 2015",
    "url": "http://royalfashion.design:80/movie/Monty/Monty123/1579001.mp4",
    "group": "Science Fiction"
  },
  {
    "name": "Comment je suis devenu super-héros - 2020",
    "url": "http://royalfashion.design:80/movie/Monty/Monty123/1579233.mkv",
    "group": "Science Fiction"
  },
  {
    "name": "Corrective Measures - 2022",
    "url": "http://royalfashion.design:80/movie/Monty/Monty123/1653161.mkv",
    "group": "Science Fiction"
  },
  {
    "name": "COVID-21: Lethal Virus - 2021",
    "url": "http://royalfashion.design:80/movie/Monty/Monty123/1578253.mp4",
    "group": "Science Fiction"
  },
  {
    "name": "Encounter - 2021",
    "url": "http://royalfashion.design:80/movie/Monty/Monty123/1576919.mp4",
    "group": "Science Fiction"
  },
  {
    "name": "Greatland - 2020",
    "url": "http://royalfashion.design:80/movie/Monty/Monty123/1577587.mp4",
    "group": "Science Fiction"
  },
  {
    "name": "Guyver: Dark Hero - 1994",
    "url": "http://royalfashion.design:80/movie/Monty/Monty123/1580221.mp4",
    "group": "Science Fiction"
  },
  {
    "name": "Infected: The Darkest Day - 2021",
    "url": "http://royalfashion.design:80/movie/Monty/Monty123/1580260.mp4",
    "group": "Science Fiction"
  },
  {
    "name": "Karmalink - 2022",
    "url": "http://royalfashion.design:80/movie/Monty/Monty123/1579298.mp4",
    "group": "Science Fiction"
  },
  {
    "name": "Moon - 2009",
    "url": "http://royalfashion.design:80/movie/Monty/Monty123/1583317.mkv",
    "group": "Science Fiction"
  },
  {
    "name": "Parallel Minds - 2020",
    "url": "http://royalfashion.design:80/movie/Monty/Monty123/1577768.mp4",
    "group": "Science Fiction"
  },
  {
    "name": "Philadelphia Experiment II - 1993",
    "url": "http://royalfashion.design:80/movie/Monty/Monty123/1578486.mp4",
    "group": "Science Fiction"
  },
  {
    "name": "Predators - 2010",
    "url": "http://royalfashion.design:80/movie/Monty/Monty123/1653603.mp4",
    "group": "Science Fiction"
  },
  {
    "name": "Primer - 2004",
    "url": "http://royalfashion.design:80/movie/Monty/Monty123/1577794.mp4",
    "group": "Science Fiction"
  },
  {
    "name": "Psycho Goreman - 2020",
    "url": "http://royalfashion.design:80/movie/Monty/Monty123/1579510.mp4",
    "group": "Science Fiction"
  },
  {
    "name": "Push - 2009",
    "url": "http://royalfashion.design:80/movie/Monty/Monty123/1578500.mkv",
    "group": "Science Fiction"
  },
  {
    "name": "Ready Player One - 2018",
    "url": "http://royalfashion.design:80/movie/Monty/Monty123/1583362.mkv",
    "group": "Science Fiction"
  },
  {
    "name": "Replicas - 2018",
    "url": "http://royalfashion.design:80/movie/Monty/Monty123/1591515.mp4",
    "group": "Science Fiction"
  },
  {
    "name": "Robot Overlords - 2015",
    "url": "http://royalfashion.design:80/movie/Monty/Monty123/1579537.mkv",
    "group": "Science Fiction"
  },
  {
    "name": "Sea Fever - 2020",
    "url": "http://royalfashion.design:80/movie/Monty/Monty123/1577850.mp4",
    "group": "Science Fiction"
  },
  {
    "name": "See You Yesterday - 2019",
    "url": "http://royalfashion.design:80/movie/Monty/Monty123/1582050.mkv",
    "group": "Science Fiction"
  },
  {
    "name": "Something in the Dirt - 2022",
    "url": "http://royalfashion.design:80/movie/Monty/Monty123/1579602.mkv",
    "group": "Science Fiction"
  },
  {
    "name": "Space - 2020",
    "url": "http://royalfashion.design:80/movie/Monty/Monty123/1583382.mkv",
    "group": "Science Fiction"
  },
  {
    "name": "Teenage Mutant Ninja Turtles - 2014",
    "url": "http://royalfashion.design:80/movie/Monty/Monty123/1577049.mp4",
    "group": "Science Fiction"
  },
  {
    "name": "The Tomorrow Job - 2023",
    "url": "http://royalfashion.design:80/movie/Monty/Monty123/1648692.mp4",
    "group": "Science Fiction"
  },
  {
    "name": "They Cloned Tyrone - 2023",
    "url": "http://royalfashion.design:80/movie/Monty/Monty123/1664210.mp4",
    "group": "Science Fiction"
  },
  {
    "name": "Worm - 2013",
    "url": "http://royalfashion.design:80/movie/Monty/Monty123/1578797.mkv",
    "group": "Science Fiction"
  },
  {
    "name": "The White King (2016)",
    "url": "http://royalfashion.design:80/movie/Monty/Monty123/1760875.mp4",
    "group": "Science Fiction"
  },
  {
    "name": "Mary Shelley's Frankenstein (1994)",
    "url": "http://royalfashion.design:80/movie/Monty/Monty123/1760237.mkv",
    "group": "Science Fiction"
  },
  {
    "name": "Brazil (1985)",
    "url": "http://royalfashion.design:80/movie/Monty/Monty123/1760219.mkv",
    "group": "Science Fiction"
  },
  {
    "name": "Voyage of the Rock Aliens - 1984",
    "url": "http://royalfashion.design:80/movie/Monty/Monty123/1734125.mp4",
    "group": "Science Fiction"
  },
  {
    "name": "WarGames: The Dead Code - 2008",
    "url": "http://royalfashion.design:80/movie/Monty/Monty123/1734054.mp4",
    "group": "Science Fiction"
  },
  {
    "name": "Beneath the Green - 2023",
    "url": "http://royalfashion.design:80/movie/Monty/Monty123/1733275.mkv",
    "group": "Science Fiction"
  },
  {
    "name": "Terminator: Dark Fate - 2019",
    "url": "http://royalfashion.design:80/movie/Monty/Monty123/1591602.mkv",
    "group": "Science Fiction"
  },
  {
    "name": "2073 (2024)",
    "url": "http://royalfashion.design:80/movie/Monty/Monty123/1780454.mp4",
    "group": "Science Fiction"
  }
]